Strings2/__init__.py
Strings2/strings.py
Strings2-0.0.4.dist-info/LICENSE
Strings2-0.0.4.dist-info/METADATA
Strings2-0.0.4.dist-info/WHEEL
Strings2-0.0.4.dist-info/top_level.txt
Strings2-0.0.4.dist-info/RECORD
